goat_monitor/__init__.py
goat_monitor/_version.py
goat_monitor/goat_monitor.py
goat_monitor-0.1.3.dist-info/METADATA
goat_monitor-0.1.3.dist-info/WHEEL
goat_monitor-0.1.3.dist-info/entry_points.txt
goat_monitor-0.1.3.dist-info/top_level.txt
goat_monitor-0.1.3.dist-info/RECORD
