Metadata-Version: 2.1
Name: goat_monitor
Version: 0.1.3
Summary: Remote monitoring of anything
Author-email: Brendan Haines <brendan.haines@gmail.com>
License: MIT License
Project-URL: homepage, https://git.brendanhaines.com/brendanhaines/goat_monitor
Classifier: Programming Language :: Python :: 3
Requires-Python: >=3
Requires-Dist: numpy
Requires-Dist: toml
Requires-Dist: click
Requires-Dist: gotify
